odoo8_addon_account_payment_mode_term-8.0.0.1.2.99.dev8-py2.7-nspkg.pth
odoo8_addon_account_payment_mode_term-8.0.0.1.2.99.dev8.dist-info/DESCRIPTION.rst
odoo8_addon_account_payment_mode_term-8.0.0.1.2.99.dev8.dist-info/METADATA
odoo8_addon_account_payment_mode_term-8.0.0.1.2.99.dev8.dist-info/RECORD
odoo8_addon_account_payment_mode_term-8.0.0.1.2.99.dev8.dist-info/WHEEL
odoo8_addon_account_payment_mode_term-8.0.0.1.2.99.dev8.dist-info/metadata.json
odoo8_addon_account_payment_mode_term-8.0.0.1.2.99.dev8.dist-info/namespace_packages.txt
odoo8_addon_account_payment_mode_term-8.0.0.1.2.99.dev8.dist-info/top_level.txt
odoo_addons/account_payment_mode_term/README.rst
odoo_addons/account_payment_mode_term/__init__.py
odoo_addons/account_payment_mode_term/__openerp__.py
odoo_addons/account_payment_mode_term/i18n/account_payment_mode_term.pot
odoo_addons/account_payment_mode_term/i18n/ca.po
odoo_addons/account_payment_mode_term/i18n/de.po
odoo_addons/account_payment_mode_term/i18n/es.po
odoo_addons/account_payment_mode_term/i18n/fi.po
odoo_addons/account_payment_mode_term/i18n/fr.po
odoo_addons/account_payment_mode_term/i18n/it.po
odoo_addons/account_payment_mode_term/i18n/nl.po
odoo_addons/account_payment_mode_term/i18n/pt_BR.po
odoo_addons/account_payment_mode_term/i18n/sl.po
odoo_addons/account_payment_mode_term/i18n/zh_CN.po
odoo_addons/account_payment_mode_term/models/__init__.py
odoo_addons/account_payment_mode_term/models/payment_mode.py
odoo_addons/account_payment_mode_term/models/payment_order_create.py
odoo_addons/account_payment_mode_term/static/description/icon.png
odoo_addons/account_payment_mode_term/views/payment_mode.xml
