Metadata-Version: 2.0
Name: odoo8-addon-account-payment-mode-term
Version: 8.0.0.1.2.99.dev8
Summary: Account Banking - Payments Term Filter
Home-page: https://github.com/OCA/banking
Author: Banking addons community,Odoo Community Association (OCA)
Author-email: support@odoo-community.org
License: AGPL-3
Platform: UNKNOWN
Classifier: Programming Language :: Python
Classifier: Framework :: Odoo
Classifier: License :: OSI Approved :: GNU Affero General Public License v3
Requires-Python: ~=2.7
Requires-Dist: odoo (<9.0a,>=8.0a)
Requires-Dist: odoo8-addon-account-banking-payment-export
